cloud_tts_tool/__init__.py
cloud_tts_tool/aws_cloud.py
cloud_tts_tool/azure_cloud.py
cloud_tts_tool/google_cloud.py
cloud_tts_tool/main.py
cloud_tts_tool/text_blocks.py
cloud_tts_tool-0.0.75.dist-info/METADATA
cloud_tts_tool-0.0.75.dist-info/WHEEL
cloud_tts_tool-0.0.75.dist-info/licenses/LICENSE
cloud_tts_tool-0.0.75.dist-info/RECORD
