Metadata-Version: 2.1
Name: cloud_tts_tool
Version: 0.0.75
Summary: A tool for requesting text to speech from a variety of cloud APIs.
Project-URL: Homepage, https://github.com/cobiadigital/cloud_tts_tools
Project-URL: Bug Tracker, https://github.com/cobiadigital/cloud_tts_tools/issues
Author-email: Ben Brenner <ben.brenner@gmail.com>
License-File: LICENSE
Classifier: License :: OSI Approved :: MIT License
Classifier: Operating System :: OS Independent
Classifier: Programming Language :: Python :: 3
Requires-Python: >=3.9
Requires-Dist: azure-cognitiveservices-speech
Requires-Dist: boto3
Requires-Dist: google-cloud-texttospeech
Requires-Dist: keyring
